LICENSE.txt
MANIFEST.in
README.rst
parse.py
setup.py
country_bounding_boxes/__init__.py
country_bounding_boxes/generated.py
country_bounding_boxes/tests.py
country_bounding_boxes.egg-info/PKG-INFO
country_bounding_boxes.egg-info/SOURCES.txt
country_bounding_boxes.egg-info/dependency_links.txt
country_bounding_boxes.egg-info/requires.txt
country_bounding_boxes.egg-info/top_level.txt
requirements/requirements.txt
requirements/tests.txt