Metadata-Version: 1.1
Name: country-bounding-boxes
Version: 0.2.3
Summary: Library of bounding boxes of countries (and associated data)
Home-page: https://github.com/graydon/country-bounding-boxes
Author: Graydon Hoare
Author-email: graydon@pobox.com
License: LICENSE.txt
Platform: UNKNOWN
Classifier: Intended Audience :: Developers
Classifier: Natural Language :: English
Classifier: Operating System :: OS Independent
Classifier: License :: OSI Approved :: Apache Software License
Classifier: Topic :: Scientific/Engineering :: GIS
Classifier: Topic :: Software Development :: Internationalization
Classifier: Programming Language :: Python
Classifier: Programming Language :: Python :: 2
Classifier: Programming Language :: Python :: 2.6
Classifier: Programming Language :: Python :: 2.7
Classifier: Programming Language :: Python :: 3
Classifier: Programming Language :: Python :: 3.3
Classifier: Programming Language :: Python :: 3.4
